{ "TIMESTAMP":1462305394, "FINAL_RESULT":0,  "MESSAGES":["Stats Check Begin"],  "TORTURE_FAILED":0,  "RUNNING_CPU_MAX":3,  "RUNNING_CPU_AVG":1,  "FINAL_CPU_MAX":1,  "FINAL_CPU_AVG":0,  "RUNNING_THREAD_MAX":191,  "RUNNING_THREAD_AVG":190,  "FINAL_THREAD_MAX":128,  "FINAL_THREAD_AVG":94,  "JVB_FINAL_STACK_THREAD_COUNT":97,  "JICOFO_FINAL_STACK_THREAD_COUNT":107,  "JVB_RUNNING_STACK_THREAD_COUNT":202,  "JICOFO_RUNNING_STACK_THREAD_COUNT":107,  "JVB_RUNNING_HEAP_SIZE":30372273,  "JVB_FINAL_HEAP_SIZE":21954317,  "JICOFO_RUNNING_HEAP_SIZE":23620955,  "JICOFO_FINAL_HEAP_SIZE":20723044,  "JICOFO_LOGFILE_SIZE":546366,  "JVB_LOGFILE_SIZE":9301140,  "JVB_LOGFILE_LINECOUNT":45095,  "JICOFO_LOGFILE_LINECOUNT":2479,  "INSTANCE_TYPE":"c4.xlarge", "JVB_VERSION":"728", "JICOFO_VERSION":"252", "JITSI_MEET_VERSION":"980", "BUILD":"237", "PIPELINE_BUILD_NUMBER":"129"}
