{ "TIMESTAMP":1497001664, "FINAL_RESULT":1,  "MESSAGES":["Stats Check Begin"],  "TORTURE_FAILED":1,  "RUNNING_CPU_MAX":33,  "RUNNING_CPU_AVG":5,  "FINAL_CPU_MAX":25,  "FINAL_CPU_AVG":3,  "RUNNING_THREAD_MAX":265,  "RUNNING_THREAD_AVG":261,  "FINAL_THREAD_MAX":112,  "FINAL_THREAD_AVG":110,  "RUNNING_BITRATE_MAX":68211,  "RUNNING_BITRATE_AVG":64624,  "FINAL_BITRATE_MAX":0,  "FINAL_BITRATE_AVG":0,  "JVB_FINAL_STACK_THREAD_COUNT":119,  "JICOFO_FINAL_STACK_THREAD_COUNT":100,  "JVB_RUNNING_STACK_THREAD_COUNT":274,  "JICOFO_RUNNING_STACK_THREAD_COUNT":100,  "JVB_RUNNING_HEAP_SIZE":67327539,  "JVB_FINAL_HEAP_SIZE":14177104,  "JICOFO_RUNNING_HEAP_SIZE":9557571,  "JICOFO_FINAL_HEAP_SIZE":8915190,  "JICOFO_LOGFILE_SIZE":555334,  "JVB_LOGFILE_SIZE":9323297,  "JVB_LOGFILE_LINECOUNT":25250,  "JICOFO_LOGFILE_LINECOUNT":3291,  "JVB_RUNNING_LSOF_LINECOUNT":341,  "JVB_FINAL_LSOF_LINECOUNT":301,  "JICOFO_RUNNING_LSOF_LINECOUNT":215,  "JICOFO_FINAL_LSOF_LINECOUNT":215,  "INSTANCE_TYPE":"c4.xlarge", "JVB_VERSION":"961", "JICOFO_VERSION":"357", "JITSI_MEET_VERSION":"2013", "BUILD":"1258", "PIPELINE_BUILD_NUMBER":"1133"}
