{ "TIMESTAMP":1477350987, "FINAL_RESULT":24,  "MESSAGES":["Stats Check Begin","JVB Final Log File Size 12257984 > 7500000","JVB Final Log File Line Count 49004 > 30000"],  "TORTURE_FAILED":0,  "RUNNING_CPU_MAX":13,  "RUNNING_CPU_AVG":3,  "FINAL_CPU_MAX":7,  "FINAL_CPU_AVG":1,  "RUNNING_THREAD_MAX":233,  "RUNNING_THREAD_AVG":230,  "FINAL_THREAD_MAX":103,  "FINAL_THREAD_AVG":102,  "RUNNING_BITRATE_MAX":68002,  "RUNNING_BITRATE_AVG":64646,  "FINAL_BITRATE_MAX":68002,  "FINAL_BITRATE_AVG":64646,  "JVB_FINAL_STACK_THREAD_COUNT":112,  "JICOFO_FINAL_STACK_THREAD_COUNT":99,  "JVB_RUNNING_STACK_THREAD_COUNT":241,  "JICOFO_RUNNING_STACK_THREAD_COUNT":99,  "JVB_RUNNING_HEAP_SIZE":47031917,  "JVB_FINAL_HEAP_SIZE":13935057,  "JICOFO_RUNNING_HEAP_SIZE":9490067,  "JICOFO_FINAL_HEAP_SIZE":8844891,  "JICOFO_LOGFILE_SIZE":369272,  "JVB_LOGFILE_SIZE":12257984,  "JVB_LOGFILE_LINECOUNT":49004,  "JICOFO_LOGFILE_LINECOUNT":2573,  "JVB_RUNNING_LSOF_LINECOUNT":312,  "JVB_FINAL_LSOF_LINECOUNT":292,  "JICOFO_RUNNING_LSOF_LINECOUNT":224,  "JICOFO_FINAL_LSOF_LINECOUNT":225,  "INSTANCE_TYPE":"c4.xlarge", "JVB_VERSION":"835", "JICOFO_VERSION":"299", "JITSI_MEET_VERSION":"1398", "BUILD":"729", "PIPELINE_BUILD_NUMBER":"607"}
