{ "TIMESTAMP":1478122156, "FINAL_RESULT":0,  "MESSAGES":["Stats Check Begin"],  "TORTURE_FAILED":0,  "RUNNING_CPU_MAX":13,  "RUNNING_CPU_AVG":3,  "FINAL_CPU_MAX":10,  "FINAL_CPU_AVG":1,  "RUNNING_THREAD_MAX":194,  "RUNNING_THREAD_AVG":192,  "FINAL_THREAD_MAX":67,  "FINAL_THREAD_AVG":66,  "RUNNING_BITRATE_MAX":67294,  "RUNNING_BITRATE_AVG":64863,  "FINAL_BITRATE_MAX":67294,  "FINAL_BITRATE_AVG":64863,  "JVB_FINAL_STACK_THREAD_COUNT":76,  "JICOFO_FINAL_STACK_THREAD_COUNT":83,  "JVB_RUNNING_STACK_THREAD_COUNT":203,  "JICOFO_RUNNING_STACK_THREAD_COUNT":83,  "JVB_RUNNING_HEAP_SIZE":46739232,  "JVB_FINAL_HEAP_SIZE":13774553,  "JICOFO_RUNNING_HEAP_SIZE":9236921,  "JICOFO_FINAL_HEAP_SIZE":8767940,  "JICOFO_LOGFILE_SIZE":418715,  "JVB_LOGFILE_SIZE":3982652,  "JVB_LOGFILE_LINECOUNT":11532,  "JICOFO_LOGFILE_LINECOUNT":3157,  "JVB_RUNNING_LSOF_LINECOUNT":312,  "JVB_FINAL_LSOF_LINECOUNT":292,  "JICOFO_RUNNING_LSOF_LINECOUNT":224,  "JICOFO_FINAL_LSOF_LINECOUNT":225,  "INSTANCE_TYPE":"c4.xlarge", "JVB_VERSION":"838", "JICOFO_VERSION":"302", "JITSI_MEET_VERSION":"1442", "BUILD":"760", "PIPELINE_BUILD_NUMBER":"638"}
